silica_django/__init__.py
silica_django/fields.py
silica_django/forms.py
silica_django/layout.py
silica_django/mixins.py
silica_django/rules.py
silica_django/templates/silica_loader.html
silica_django/templatetags/__init__.py
silica_django/templatetags/silica.py
silica_django/utils/__init__.py
silica_django/utils/jsonschema.py
silica_django-0.0.4.dist-info/LICENSE
silica_django-0.0.4.dist-info/METADATA
silica_django-0.0.4.dist-info/WHEEL
silica_django-0.0.4.dist-info/top_level.txt
silica_django-0.0.4.dist-info/RECORD
