Metadata-Version: 2.1
Name: silica-django
Version: 0.0.4
Summary: Library which translates Django Forms into JSON for use with frontend libraries implementing JSONSchema and, optionally, JsonForm's UISchema
Home-page: https://github.com/zagaran/silica-django
Author: Zagaran, Inc.
License: MIT
Keywords: django jsonforms forms silica_django
Platform: UNKNOWN
Classifier: Development Status :: 4 - Beta
Classifier: License :: OSI Approved :: MIT License
Classifier: Operating System :: MacOS :: MacOS X
Classifier: Operating System :: Microsoft :: Windows
Classifier: Operating System :: POSIX
Classifier: Programming Language :: Python
License-File: LICENSE
Requires-Dist: django (>=3.2)
